{"ConceptSets":[{"id":0,"name":"Ischemic stroke","expression":{"items":[{"concept":{"CONCEPT_ID":443454,"CONCEPT_NAME":"Cerebral infarction","STANDARD_CONCEPT":"S","STANDARD_CONCEPT_CAPTION":"Standard","INVALID_REASON":"V","INVALID_REASON_CAPTION":"Valid","CONCEPT_CODE":"432504007","DOMAIN_ID":"Condition","VOCABULARY_ID":"SNOMED","CONCEPT_CLASS_ID":"Clinical Finding"},"includeDescendants":true},{"concept":{"CONCEPT_ID":4043731,"CONCEPT_NAME":"Infarction - precerebral","STANDARD_CONCEPT":"S","STANDARD_CONCEPT_CAPTION":"Standard","INVALID_REASON":"V","INVALID_REASON_CAPTION":"Valid","CONCEPT_CODE":"230692004","DOMAIN_ID":"Condition","VOCABULARY_ID":"SNOMED","CONCEPT_CLASS_ID":"Clinical Finding"},"includeDescendants":true}]}}],"PrimaryCriteria":{"CriteriaList":[{"ConditionOccurrence":{"CodesetId":0}}],"ObservationWindow":{"PriorDays":0,"PostDays":0},"PrimaryCriteriaLimit":{"Type":"All"}},"QualifiedLimit":{"Type":"First"},"ExpressionLimit":{"Type":"All"},"InclusionRules":[],"EndStrategy":{"DateOffset":{"DateField":"StartDate","Offset":1}},"CensoringCriteria":[],"CollapseSettings":{"CollapseType":"ERA","EraPad":0},"CensorWindow":{}}
