{
	"cdmVersionRange" : ">=5.0.0",
	"PrimaryCriteria" : {
		"CriteriaList" : [
			{
				"ConditionOccurrence" : {
					"CodesetId" : 0,
					"ConditionTypeExclude" : false
				}
			}
		],
		"ObservationWindow" : {
			"PriorDays" : 0,
			"PostDays" : 0
		},
		"PrimaryCriteriaLimit" : {
			"Type" : "All"
		}
	},
	"ConceptSets" : [
		{
			"id" : 0,
			"name" : "[epi980] edema",
			"expression" : {
				"items" : [
					{
						"concept" : {
							"CONCEPT_ID" : 433595,
							"CONCEPT_NAME" : "Edema",
							"STANDARD_CONCEPT" : "S",
							"STANDARD_CONCEPT_CAPTION" : "Standard",
							"INVALID_REASON" : "V",
							"INVALID_REASON_CAPTION" : "Valid",
							"CONCEPT_CODE" : "267038008",
							"DOMAIN_ID" : "Condition",
							"VOCABULARY_ID" : "SNOMED",
							"CONCEPT_CLASS_ID" : "Clinical Finding"
						},
						"isExcluded" : false,
						"includeDescendants" : true,
						"includeMapped" : false
					},
					{
						"concept" : {
							"CONCEPT_ID" : 4297361,
							"CONCEPT_NAME" : "Angioedema and/or urticaria",
							"STANDARD_CONCEPT" : "S",
							"STANDARD_CONCEPT_CAPTION" : "Standard",
							"INVALID_REASON" : "V",
							"INVALID_REASON_CAPTION" : "Valid",
							"CONCEPT_CODE" : "404177007",
							"DOMAIN_ID" : "Condition",
							"VOCABULARY_ID" : "SNOMED",
							"CONCEPT_CLASS_ID" : "Clinical Finding"
						},
						"isExcluded" : true,
						"includeDescendants" : true,
						"includeMapped" : false
					},
					{
						"concept" : {
							"CONCEPT_ID" : 4317260,
							"CONCEPT_NAME" : "Edematous skin",
							"STANDARD_CONCEPT" : "S",
							"STANDARD_CONCEPT_CAPTION" : "Standard",
							"INVALID_REASON" : "V",
							"INVALID_REASON_CAPTION" : "Valid",
							"CONCEPT_CODE" : "95322002",
							"DOMAIN_ID" : "Condition",
							"VOCABULARY_ID" : "SNOMED",
							"CONCEPT_CLASS_ID" : "Clinical Finding"
						},
						"isExcluded" : true,
						"includeDescendants" : true,
						"includeMapped" : false
					},
					{
						"concept" : {
							"CONCEPT_ID" : 376690,
							"CONCEPT_NAME" : "Cerebral edema",
							"STANDARD_CONCEPT" : "S",
							"STANDARD_CONCEPT_CAPTION" : "Standard",
							"INVALID_REASON" : "V",
							"INVALID_REASON_CAPTION" : "Valid",
							"CONCEPT_CODE" : "2032001",
							"DOMAIN_ID" : "Condition",
							"VOCABULARY_ID" : "SNOMED",
							"CONCEPT_CLASS_ID" : "Clinical Finding"
						},
						"isExcluded" : true,
						"includeDescendants" : true,
						"includeMapped" : false
					},
					{
						"concept" : {
							"CONCEPT_ID" : 4078925,
							"CONCEPT_NAME" : "Pulmonary edema",
							"STANDARD_CONCEPT" : "S",
							"STANDARD_CONCEPT_CAPTION" : "Standard",
							"INVALID_REASON" : "V",
							"INVALID_REASON_CAPTION" : "Valid",
							"CONCEPT_CODE" : "19242006",
							"DOMAIN_ID" : "Condition",
							"VOCABULARY_ID" : "SNOMED",
							"CONCEPT_CLASS_ID" : "Clinical Finding"
						},
						"isExcluded" : true,
						"includeDescendants" : true,
						"includeMapped" : false
					},
					{
						"concept" : {
							"CONCEPT_ID" : 372903,
							"CONCEPT_NAME" : "Retinal edema",
							"STANDARD_CONCEPT" : "S",
							"STANDARD_CONCEPT_CAPTION" : "Standard",
							"INVALID_REASON" : "V",
							"INVALID_REASON_CAPTION" : "Valid",
							"CONCEPT_CODE" : "6141006",
							"DOMAIN_ID" : "Condition",
							"VOCABULARY_ID" : "SNOMED",
							"CONCEPT_CLASS_ID" : "Clinical Finding"
						},
						"isExcluded" : true,
						"includeDescendants" : true,
						"includeMapped" : false
					},
					{
						"concept" : {
							"CONCEPT_ID" : 380102,
							"CONCEPT_NAME" : "Corneal edema",
							"STANDARD_CONCEPT" : "S",
							"STANDARD_CONCEPT_CAPTION" : "Standard",
							"INVALID_REASON" : "V",
							"INVALID_REASON_CAPTION" : "Valid",
							"CONCEPT_CODE" : "27194006",
							"DOMAIN_ID" : "Condition",
							"VOCABULARY_ID" : "SNOMED",
							"CONCEPT_CLASS_ID" : "Clinical Finding"
						},
						"isExcluded" : true,
						"includeDescendants" : true,
						"includeMapped" : false
					},
					{
						"concept" : {
							"CONCEPT_ID" : 40482052,
							"CONCEPT_NAME" : "Edema of face",
							"STANDARD_CONCEPT" : "S",
							"STANDARD_CONCEPT_CAPTION" : "Standard",
							"INVALID_REASON" : "V",
							"INVALID_REASON_CAPTION" : "Valid",
							"CONCEPT_CODE" : "445088006",
							"DOMAIN_ID" : "Condition",
							"VOCABULARY_ID" : "SNOMED",
							"CONCEPT_CLASS_ID" : "Clinical Finding"
						},
						"isExcluded" : true,
						"includeDescendants" : true,
						"includeMapped" : false
					},
					{
						"concept" : {
							"CONCEPT_ID" : 22350,
							"CONCEPT_NAME" : "Edema of larynx",
							"STANDARD_CONCEPT" : "S",
							"STANDARD_CONCEPT_CAPTION" : "Standard",
							"INVALID_REASON" : "V",
							"INVALID_REASON_CAPTION" : "Valid",
							"CONCEPT_CODE" : "51599000",
							"DOMAIN_ID" : "Condition",
							"VOCABULARY_ID" : "SNOMED",
							"CONCEPT_CLASS_ID" : "Clinical Finding"
						},
						"isExcluded" : true,
						"includeDescendants" : true,
						"includeMapped" : false
					},
					{
						"concept" : {
							"CONCEPT_ID" : 438178,
							"CONCEPT_NAME" : "Postmastectomy lymphedema syndrome",
							"STANDARD_CONCEPT" : "S",
							"STANDARD_CONCEPT_CAPTION" : "Standard",
							"INVALID_REASON" : "V",
							"INVALID_REASON_CAPTION" : "Valid",
							"CONCEPT_CODE" : "33129002",
							"DOMAIN_ID" : "Condition",
							"VOCABULARY_ID" : "SNOMED",
							"CONCEPT_CLASS_ID" : "Clinical Finding"
						},
						"isExcluded" : true,
						"includeDescendants" : true,
						"includeMapped" : false
					}
				]
			}
		}
	],
	"QualifiedLimit" : {
		"Type" : "First"
	},
	"ExpressionLimit" : {
		"Type" : "All"
	},
	"InclusionRules" : [
		{
			"name" : "30 day washout",
			"expression" : {
				"Type" : "ALL",
				"CriteriaList" : [
					{
						"Criteria" : {
							"ConditionOccurrence" : {
								"CodesetId" : 0,
								"ConditionTypeExclude" : false
							}
						},
						"StartWindow" : {
							"Start" : {
								"Days" : 30,
								"Coeff" : -1
							},
							"End" : {
								"Days" : 1,
								"Coeff" : -1
							},
							"UseIndexEnd" : false,
							"UseEventEnd" : false
						},
						"RestrictVisit" : false,
						"IgnoreObservationPeriod" : false,
						"Occurrence" : {
							"Type" : 0,
							"Count" : 0,
							"IsDistinct" : false
						}
					}
				],
				"DemographicCriteriaList" : [],
				"Groups" : []
			}
		}
	],
	"EndStrategy" : {
		"DateOffset" : {
			"DateField" : "StartDate",
			"Offset" : 3
		}
	},
	"CensoringCriteria" : [],
	"CollapseSettings" : {
		"CollapseType" : "ERA",
		"EraPad" : 0
	},
	"CensorWindow" : {}
}