{
	"cdmVersionRange" : ">=5.0.0",
	"PrimaryCriteria" : {
		"CriteriaList" : [
			{
				"ProcedureOccurrence" : {
					"CodesetId" : 0,
					"ProcedureTypeExclude" : false
				}
			},
			{
				"Observation" : {
					"CodesetId" : 0,
					"ObservationTypeExclude" : false
				}
			}
		],
		"ObservationWindow" : {
			"PriorDays" : 0,
			"PostDays" : 0
		},
		"PrimaryCriteriaLimit" : {
			"Type" : "All"
		}
	},
	"ConceptSets" : [
		{
			"id" : 0,
			"name" : "group therapy",
			"expression" : {
				"items" : [
					{
						"concept" : {
							"CONCEPT_ID" : 2795873,
							"CONCEPT_NAME" : "Substance Abuse Treatment, Group Counseling",
							"STANDARD_CONCEPT" : "S",
							"STANDARD_CONCEPT_CAPTION" : "Standard",
							"INVALID_REASON" : "V",
							"INVALID_REASON_CAPTION" : "Valid",
							"CONCEPT_CODE" : "HZ4",
							"DOMAIN_ID" : "Procedure",
							"VOCABULARY_ID" : "ICD10PCS",
							"CONCEPT_CLASS_ID" : "ICD10PCS Hierarchy"
						},
						"isExcluded" : false,
						"includeDescendants" : true,
						"includeMapped" : false
					},
					{
						"concept" : {
							"CONCEPT_ID" : 4079501,
							"CONCEPT_NAME" : "Aversion therapy - alcoholism",
							"STANDARD_CONCEPT" : "S",
							"STANDARD_CONCEPT_CAPTION" : "Standard",
							"INVALID_REASON" : "V",
							"INVALID_REASON_CAPTION" : "Valid",
							"CONCEPT_CODE" : "183388004",
							"DOMAIN_ID" : "Procedure",
							"VOCABULARY_ID" : "SNOMED",
							"CONCEPT_CLASS_ID" : "Procedure"
						},
						"isExcluded" : false,
						"includeDescendants" : false,
						"includeMapped" : false
					},
					{
						"concept" : {
							"CONCEPT_ID" : 1552629,
							"CONCEPT_NAME" : "Group psychotherapy service for diagnosis, evaluation, or treatment of a mental health or substance use disorder provided remotely by hospital staff who are licensed to provide mental health services under applicable state law(s), when the patient is i...",
							"STANDARD_CONCEPT" : "S",
							"STANDARD_CONCEPT_CAPTION" : "Standard",
							"INVALID_REASON" : "V",
							"INVALID_REASON_CAPTION" : "Valid",
							"CONCEPT_CODE" : "C7903",
							"DOMAIN_ID" : "Observation",
							"VOCABULARY_ID" : "HCPCS",
							"CONCEPT_CLASS_ID" : "HCPCS"
						},
						"isExcluded" : false,
						"includeDescendants" : false,
						"includeMapped" : false
					},
					{
						"concept" : {
							"CONCEPT_ID" : 2213548,
							"CONCEPT_NAME" : "Group psychotherapy (other than of a multiple-family group)",
							"STANDARD_CONCEPT" : "S",
							"STANDARD_CONCEPT_CAPTION" : "Standard",
							"INVALID_REASON" : "V",
							"INVALID_REASON_CAPTION" : "Valid",
							"CONCEPT_CODE" : "90853",
							"DOMAIN_ID" : "Procedure",
							"VOCABULARY_ID" : "CPT4",
							"CONCEPT_CLASS_ID" : "CPT4"
						},
						"isExcluded" : false,
						"includeDescendants" : false,
						"includeMapped" : false
					},
					{
						"concept" : {
							"CONCEPT_ID" : 4296166,
							"CONCEPT_NAME" : "Group psychotherapy",
							"STANDARD_CONCEPT" : "S",
							"STANDARD_CONCEPT_CAPTION" : "Standard",
							"INVALID_REASON" : "V",
							"INVALID_REASON_CAPTION" : "Valid",
							"CONCEPT_CODE" : "76168009",
							"DOMAIN_ID" : "Procedure",
							"VOCABULARY_ID" : "SNOMED",
							"CONCEPT_CLASS_ID" : "Procedure"
						},
						"isExcluded" : false,
						"includeDescendants" : true,
						"includeMapped" : false
					}
				]
			}
		}
	],
	"QualifiedLimit" : {
		"Type" : "First"
	},
	"ExpressionLimit" : {
		"Type" : "All"
	},
	"InclusionRules" : [],
	"EndStrategy" : {
		"DateOffset" : {
			"DateField" : "EndDate",
			"Offset" : 0
		}
	},
	"CensoringCriteria" : [],
	"CollapseSettings" : {
		"CollapseType" : "ERA",
		"EraPad" : 30
	},
	"CensorWindow" : {}
}