{
	"cdmVersionRange" : ">=5.0.0",
	"PrimaryCriteria" : {
		"CriteriaList" : [
			{
				"ConditionOccurrence" : {
					"CodesetId" : 4,
					"ConditionTypeExclude" : false
				}
			}
		],
		"ObservationWindow" : {
			"PriorDays" : 0,
			"PostDays" : 0
		},
		"PrimaryCriteriaLimit" : {
			"Type" : "All"
		}
	},
	"ConceptSets" : [
		{
			"id" : 4,
			"name" : "Tinnitus ",
			"expression" : {
				"items" : [
					{
						"concept" : {
							"CONCEPT_ID" : 4339486,
							"CONCEPT_NAME" : "Noise-induced tinnitus",
							"STANDARD_CONCEPT" : "S",
							"STANDARD_CONCEPT_CAPTION" : "Standard",
							"INVALID_REASON" : "V",
							"INVALID_REASON_CAPTION" : "Valid",
							"CONCEPT_CODE" : "232318001",
							"DOMAIN_ID" : "Condition",
							"VOCABULARY_ID" : "SNOMED",
							"CONCEPT_CLASS_ID" : "Clinical Finding"
						},
						"isExcluded" : false,
						"includeDescendants" : true,
						"includeMapped" : false
					},
					{
						"concept" : {
							"CONCEPT_ID" : 377575,
							"CONCEPT_NAME" : "Tinnitus",
							"STANDARD_CONCEPT" : "S",
							"STANDARD_CONCEPT_CAPTION" : "Standard",
							"INVALID_REASON" : "V",
							"INVALID_REASON_CAPTION" : "Valid",
							"CONCEPT_CODE" : "60862001",
							"DOMAIN_ID" : "Condition",
							"VOCABULARY_ID" : "SNOMED",
							"CONCEPT_CLASS_ID" : "Clinical Finding"
						},
						"isExcluded" : false,
						"includeDescendants" : true,
						"includeMapped" : false
					},
					{
						"concept" : {
							"CONCEPT_ID" : 4339487,
							"CONCEPT_NAME" : "Tinnitus of muscular origin",
							"STANDARD_CONCEPT" : "S",
							"STANDARD_CONCEPT_CAPTION" : "Standard",
							"INVALID_REASON" : "V",
							"INVALID_REASON_CAPTION" : "Valid",
							"CONCEPT_CODE" : "232319009",
							"DOMAIN_ID" : "Condition",
							"VOCABULARY_ID" : "SNOMED",
							"CONCEPT_CLASS_ID" : "Clinical Finding"
						},
						"isExcluded" : false,
						"includeDescendants" : true,
						"includeMapped" : false
					},
					{
						"concept" : {
							"CONCEPT_ID" : 4339489,
							"CONCEPT_NAME" : "Tinnitus of vascular origin",
							"STANDARD_CONCEPT" : "S",
							"STANDARD_CONCEPT_CAPTION" : "Standard",
							"INVALID_REASON" : "V",
							"INVALID_REASON_CAPTION" : "Valid",
							"CONCEPT_CODE" : "232322006",
							"DOMAIN_ID" : "Condition",
							"VOCABULARY_ID" : "SNOMED",
							"CONCEPT_CLASS_ID" : "Clinical Finding"
						},
						"isExcluded" : false,
						"includeDescendants" : true,
						"includeMapped" : false
					},
					{
						"concept" : {
							"CONCEPT_ID" : 4036628,
							"CONCEPT_NAME" : "Ringing in ear",
							"STANDARD_CONCEPT" : "S",
							"STANDARD_CONCEPT_CAPTION" : "Standard",
							"INVALID_REASON" : "V",
							"INVALID_REASON_CAPTION" : "Valid",
							"CONCEPT_CODE" : "162352007",
							"DOMAIN_ID" : "Condition",
							"VOCABULARY_ID" : "SNOMED",
							"CONCEPT_CLASS_ID" : "Clinical Finding"
						},
						"isExcluded" : false,
						"includeDescendants" : true,
						"includeMapped" : false
					},
					{
						"concept" : {
							"CONCEPT_ID" : 4037309,
							"CONCEPT_NAME" : "Noises in ear",
							"STANDARD_CONCEPT" : "S",
							"STANDARD_CONCEPT_CAPTION" : "Standard",
							"INVALID_REASON" : "V",
							"INVALID_REASON_CAPTION" : "Valid",
							"CONCEPT_CODE" : "162349004",
							"DOMAIN_ID" : "Condition",
							"VOCABULARY_ID" : "SNOMED",
							"CONCEPT_CLASS_ID" : "Clinical Finding"
						},
						"isExcluded" : false,
						"includeDescendants" : true,
						"includeMapped" : false
					},
					{
						"concept" : {
							"CONCEPT_ID" : 4048162,
							"CONCEPT_NAME" : "Tinnitus due to spontaneous oto-acoustic emission",
							"STANDARD_CONCEPT" : "S",
							"STANDARD_CONCEPT_CAPTION" : "Standard",
							"INVALID_REASON" : "V",
							"INVALID_REASON_CAPTION" : "Valid",
							"CONCEPT_CODE" : "232323001",
							"DOMAIN_ID" : "Condition",
							"VOCABULARY_ID" : "SNOMED",
							"CONCEPT_CLASS_ID" : "Clinical Finding"
						},
						"isExcluded" : false,
						"includeDescendants" : true,
						"includeMapped" : false
					}
				]
			}
		}
	],
	"QualifiedLimit" : {
		"Type" : "All"
	},
	"ExpressionLimit" : {
		"Type" : "All"
	},
	"InclusionRules" : [],
	"EndStrategy" : {
		"DateOffset" : {
			"DateField" : "EndDate",
			"Offset" : 1
		}
	},
	"CensoringCriteria" : [],
	"CollapseSettings" : {
		"CollapseType" : "ERA",
		"EraPad" : 180
	},
	"CensorWindow" : {}
}