{
	"cdmVersionRange" : ">=5.0.0",
	"PrimaryCriteria" : {
		"CriteriaList" : [
			{
				"VisitOccurrence" : {
					"CodesetId" : 0,
					"VisitTypeExclude" : false
				}
			},
			{
				"VisitOccurrence" : {
					"CorrelatedCriteria" : {
						"Type" : "ANY",
						"CriteriaList" : [
							{
								"Criteria" : {
									"Observation" : {
										"CodesetId" : 1,
										"ObservationTypeExclude" : false
									}
								},
								"StartWindow" : {
									"Start" : {
										"Coeff" : -1
									},
									"End" : {
										"Days" : 0,
										"Coeff" : -1
									},
									"UseIndexEnd" : true,
									"UseEventEnd" : false
								},
								"EndWindow" : {
									"Start" : {
										"Days" : 0,
										"Coeff" : 1
									},
									"End" : {
										"Coeff" : 1
									},
									"UseIndexEnd" : false,
									"UseEventEnd" : false
								},
								"RestrictVisit" : false,
								"IgnoreObservationPeriod" : false,
								"Occurrence" : {
									"Type" : 2,
									"Count" : 1,
									"IsDistinct" : false
								}
							},
							{
								"Criteria" : {
									"ProcedureOccurrence" : {
										"CodesetId" : 1,
										"ProcedureTypeExclude" : false
									}
								},
								"StartWindow" : {
									"Start" : {
										"Coeff" : -1
									},
									"End" : {
										"Days" : 0,
										"Coeff" : -1
									},
									"UseIndexEnd" : false,
									"UseEventEnd" : false
								},
								"EndWindow" : {
									"Start" : {
										"Days" : 0,
										"Coeff" : 1
									},
									"End" : {
										"Coeff" : 1
									},
									"UseIndexEnd" : false,
									"UseEventEnd" : false
								},
								"RestrictVisit" : false,
								"IgnoreObservationPeriod" : false,
								"Occurrence" : {
									"Type" : 2,
									"Count" : 1,
									"IsDistinct" : false
								}
							}
						],
						"DemographicCriteriaList" : [],
						"Groups" : []
					},
					"CodesetId" : 2,
					"VisitTypeExclude" : false
				}
			},
			{
				"ProcedureOccurrence" : {
					"CodesetId" : 1,
					"ProcedureTypeExclude" : false
				}
			},
			{
				"Observation" : {
					"CodesetId" : 1,
					"ObservationTypeExclude" : false
				}
			}
		],
		"ObservationWindow" : {
			"PriorDays" : 0,
			"PostDays" : 0
		},
		"PrimaryCriteriaLimit" : {
			"Type" : "All"
		}
	},
	"ConceptSets" : [
		{
			"id" : 0,
			"name" : "Emergency room",
			"expression" : {
				"items" : [
					{
						"concept" : {
							"CONCEPT_ID" : 9203,
							"CONCEPT_NAME" : "Emergency Room Visit",
							"STANDARD_CONCEPT" : "S",
							"STANDARD_CONCEPT_CAPTION" : "Standard",
							"INVALID_REASON" : "V",
							"INVALID_REASON_CAPTION" : "Valid",
							"CONCEPT_CODE" : "ER",
							"DOMAIN_ID" : "Visit",
							"VOCABULARY_ID" : "Visit",
							"CONCEPT_CLASS_ID" : "Visit"
						},
						"isExcluded" : false,
						"includeDescendants" : true,
						"includeMapped" : false
					}
				]
			}
		},
		{
			"id" : 1,
			"name" : "Emergent or Urgent care concepts",
			"expression" : {
				"items" : [
					{
						"concept" : {
							"CONCEPT_ID" : 45890237,
							"CONCEPT_NAME" : "Emergency Department Services",
							"STANDARD_CONCEPT" : "C",
							"STANDARD_CONCEPT_CAPTION" : "Classification",
							"INVALID_REASON" : "V",
							"INVALID_REASON_CAPTION" : "Valid",
							"CONCEPT_CODE" : "1013711",
							"DOMAIN_ID" : "Observation",
							"VOCABULARY_ID" : "CPT4",
							"CONCEPT_CLASS_ID" : "CPT4 Hierarchy"
						},
						"isExcluded" : false,
						"includeDescendants" : true,
						"includeMapped" : false
					},
					{
						"concept" : {
							"CONCEPT_ID" : 4163685,
							"CONCEPT_NAME" : "Emergency department patient visit",
							"STANDARD_CONCEPT" : "S",
							"STANDARD_CONCEPT_CAPTION" : "Standard",
							"INVALID_REASON" : "V",
							"INVALID_REASON_CAPTION" : "Valid",
							"CONCEPT_CODE" : "4525004",
							"DOMAIN_ID" : "Observation",
							"VOCABULARY_ID" : "SNOMED",
							"CONCEPT_CLASS_ID" : "Procedure"
						},
						"isExcluded" : false,
						"includeDescendants" : true,
						"includeMapped" : false
					}
				]
			}
		},
		{
			"id" : 2,
			"name" : "Main Visit Categories",
			"expression" : {
				"items" : [
					{
						"concept" : {
							"CONCEPT_ID" : 9203,
							"CONCEPT_NAME" : "Emergency Room Visit",
							"STANDARD_CONCEPT" : "S",
							"STANDARD_CONCEPT_CAPTION" : "Standard",
							"INVALID_REASON" : "V",
							"INVALID_REASON_CAPTION" : "Valid",
							"CONCEPT_CODE" : "ER",
							"DOMAIN_ID" : "Visit",
							"VOCABULARY_ID" : "Visit",
							"CONCEPT_CLASS_ID" : "Visit"
						},
						"isExcluded" : false,
						"includeDescendants" : true,
						"includeMapped" : false
					},
					{
						"concept" : {
							"CONCEPT_ID" : 9201,
							"CONCEPT_NAME" : "Inpatient Visit",
							"STANDARD_CONCEPT" : "S",
							"STANDARD_CONCEPT_CAPTION" : "Standard",
							"INVALID_REASON" : "V",
							"INVALID_REASON_CAPTION" : "Valid",
							"CONCEPT_CODE" : "IP",
							"DOMAIN_ID" : "Visit",
							"VOCABULARY_ID" : "Visit",
							"CONCEPT_CLASS_ID" : "Visit"
						},
						"isExcluded" : false,
						"includeDescendants" : true,
						"includeMapped" : false
					},
					{
						"concept" : {
							"CONCEPT_ID" : 9202,
							"CONCEPT_NAME" : "Outpatient Visit",
							"STANDARD_CONCEPT" : "S",
							"STANDARD_CONCEPT_CAPTION" : "Standard",
							"INVALID_REASON" : "V",
							"INVALID_REASON_CAPTION" : "Valid",
							"CONCEPT_CODE" : "OP",
							"DOMAIN_ID" : "Visit",
							"VOCABULARY_ID" : "Visit",
							"CONCEPT_CLASS_ID" : "Visit"
						},
						"isExcluded" : false,
						"includeDescendants" : true,
						"includeMapped" : false
					},
					{
						"concept" : {
							"CONCEPT_ID" : 262,
							"CONCEPT_NAME" : "Emergency Room and Inpatient Visit",
							"STANDARD_CONCEPT" : "S",
							"STANDARD_CONCEPT_CAPTION" : "Standard",
							"INVALID_REASON" : "V",
							"INVALID_REASON_CAPTION" : "Valid",
							"CONCEPT_CODE" : "ERIP",
							"DOMAIN_ID" : "Visit",
							"VOCABULARY_ID" : "Visit",
							"CONCEPT_CLASS_ID" : "Visit"
						},
						"isExcluded" : false,
						"includeDescendants" : true,
						"includeMapped" : false
					},
					{
						"concept" : {
							"CONCEPT_ID" : 9203,
							"CONCEPT_NAME" : "Emergency Room Visit",
							"STANDARD_CONCEPT" : "S",
							"STANDARD_CONCEPT_CAPTION" : "Standard",
							"INVALID_REASON" : "V",
							"INVALID_REASON_CAPTION" : "Valid",
							"CONCEPT_CODE" : "ER",
							"DOMAIN_ID" : "Visit",
							"VOCABULARY_ID" : "Visit",
							"CONCEPT_CLASS_ID" : "Visit"
						},
						"isExcluded" : false,
						"includeDescendants" : true,
						"includeMapped" : false
					}
				]
			}
		}
	],
	"QualifiedLimit" : {
		"Type" : "All"
	},
	"ExpressionLimit" : {
		"Type" : "All"
	},
	"InclusionRules" : [],
	"EndStrategy" : {
		"DateOffset" : {
			"DateField" : "EndDate",
			"Offset" : 0
		}
	},
	"CensoringCriteria" : [],
	"CollapseSettings" : {
		"CollapseType" : "ERA",
		"EraPad" : 0
	},
	"CensorWindow" : {}
}