{
	"cdmVersionRange" : ">=5.0.0",
	"PrimaryCriteria" : {
		"CriteriaList" : [
			{
				"ConditionOccurrence" : {
					"CodesetId" : 0,
					"ConditionTypeExclude" : false
				}
			}
		],
		"ObservationWindow" : {
			"PriorDays" : 0,
			"PostDays" : 0
		},
		"PrimaryCriteriaLimit" : {
			"Type" : "First"
		}
	},
	"ConceptSets" : [
		{
			"id" : 0,
			"name" : "Optic nerve glioma",
			"expression" : {
				"items" : [
					{
						"concept" : {
							"CONCEPT_ID" : 4112970,
							"CONCEPT_NAME" : "Optic nerve glioma",
							"STANDARD_CONCEPT" : "S",
							"STANDARD_CONCEPT_CAPTION" : "Standard",
							"INVALID_REASON" : "V",
							"INVALID_REASON_CAPTION" : "Valid",
							"CONCEPT_CODE" : "254976006",
							"DOMAIN_ID" : "Condition",
							"VOCABULARY_ID" : "SNOMED",
							"CONCEPT_CLASS_ID" : "Clinical Finding"
						},
						"isExcluded" : false,
						"includeDescendants" : true,
						"includeMapped" : false
					}
				]
			}
		},
		{
			"id" : 1,
			"name" : "Neurofibromatosis Syndrome",
			"expression" : {
				"items" : [
					{
						"concept" : {
							"CONCEPT_ID" : 376938,
							"CONCEPT_NAME" : "Neurofibromatosis syndrome",
							"STANDARD_CONCEPT" : "S",
							"STANDARD_CONCEPT_CAPTION" : "Standard",
							"INVALID_REASON" : "V",
							"INVALID_REASON_CAPTION" : "Valid",
							"CONCEPT_CODE" : "19133005",
							"DOMAIN_ID" : "Condition",
							"VOCABULARY_ID" : "SNOMED",
							"CONCEPT_CLASS_ID" : "Clinical Finding"
						},
						"isExcluded" : false,
						"includeDescendants" : true,
						"includeMapped" : false
					}
				]
			}
		}
	],
	"QualifiedLimit" : {
		"Type" : "First"
	},
	"ExpressionLimit" : {
		"Type" : "First"
	},
	"InclusionRules" : [
		{
			"name" : "Neurofibromatosis",
			"description" : "Anytime in persons history",
			"expression" : {
				"Type" : "ALL",
				"CriteriaList" : [
					{
						"Criteria" : {
							"ConditionOccurrence" : {
								"CodesetId" : 1,
								"ConditionTypeExclude" : false
							}
						},
						"StartWindow" : {
							"Start" : {
								"Coeff" : -1
							},
							"End" : {
								"Coeff" : 1
							},
							"UseIndexEnd" : false,
							"UseEventEnd" : false
						},
						"RestrictVisit" : false,
						"IgnoreObservationPeriod" : false,
						"Occurrence" : {
							"Type" : 2,
							"Count" : 1,
							"IsDistinct" : false
						}
					}
				],
				"DemographicCriteriaList" : [],
				"Groups" : []
			}
		}
	],
	"CensoringCriteria" : [],
	"CollapseSettings" : {
		"CollapseType" : "ERA",
		"EraPad" : 0
	},
	"CensorWindow" : {}
}