{
	"cdmVersionRange" : ">=5.0.0",
	"PrimaryCriteria" : {
		"CriteriaList" : [
			{
				"VisitOccurrence" : {
					"CodesetId" : 0,
					"VisitTypeExclude" : false
				}
			}
		],
		"ObservationWindow" : {
			"PriorDays" : 0,
			"PostDays" : 0
		},
		"PrimaryCriteriaLimit" : {
			"Type" : "First"
		}
	},
	"AdditionalCriteria" : {
		"Type" : "ALL",
		"CriteriaList" : [
			{
				"Criteria" : {
					"ConditionOccurrence" : {
						"CodesetId" : 1,
						"ConditionTypeExclude" : false
					}
				},
				"StartWindow" : {
					"Start" : {
						"Days" : 0,
						"Coeff" : -1
					},
					"End" : {
						"Coeff" : 1
					},
					"UseIndexEnd" : false,
					"UseEventEnd" : false
				},
				"EndWindow" : {
					"Start" : {
						"Coeff" : -1
					},
					"End" : {
						"Days" : 0,
						"Coeff" : 1
					},
					"UseIndexEnd" : true,
					"UseEventEnd" : false
				},
				"RestrictVisit" : false,
				"IgnoreObservationPeriod" : false,
				"Occurrence" : {
					"Type" : 2,
					"Count" : 1,
					"IsDistinct" : false
				}
			}
		],
		"DemographicCriteriaList" : [],
		"Groups" : []
	},
	"ConceptSets" : [
		{
			"id" : 0,
			"name" : "Inpatient or Inpatient/ER visit - SF",
			"expression" : {
				"items" : [
					{
						"concept" : {
							"CONCEPT_ID" : 262,
							"CONCEPT_NAME" : "Emergency Room and Inpatient Visit",
							"STANDARD_CONCEPT" : "S",
							"STANDARD_CONCEPT_CAPTION" : "Standard",
							"INVALID_REASON" : "V",
							"INVALID_REASON_CAPTION" : "Valid",
							"CONCEPT_CODE" : "ERIP",
							"DOMAIN_ID" : "Visit",
							"VOCABULARY_ID" : "Visit",
							"CONCEPT_CLASS_ID" : "Visit"
						},
						"isExcluded" : false,
						"includeDescendants" : true,
						"includeMapped" : false
					},
					{
						"concept" : {
							"CONCEPT_ID" : 9201,
							"CONCEPT_NAME" : "Inpatient Visit",
							"STANDARD_CONCEPT" : "S",
							"STANDARD_CONCEPT_CAPTION" : "Standard",
							"INVALID_REASON" : "V",
							"INVALID_REASON_CAPTION" : "Valid",
							"CONCEPT_CODE" : "IP",
							"DOMAIN_ID" : "Visit",
							"VOCABULARY_ID" : "Visit",
							"CONCEPT_CLASS_ID" : "Visit"
						},
						"isExcluded" : false,
						"includeDescendants" : true,
						"includeMapped" : false
					}
				]
			}
		},
		{
			"id" : 1,
			"name" : "Epilepsy (from ICD10 Codes)",
			"expression" : {
				"items" : [
					{
						"concept" : {
							"CONCEPT_ID" : 4101747,
							"CONCEPT_NAME" : "Localization-related(focal)(partial)idiopathic epilepsy and epileptic syndromes with seizures of localized onset",
							"STANDARD_CONCEPT" : "S",
							"STANDARD_CONCEPT_CAPTION" : "Standard",
							"INVALID_REASON" : "V",
							"INVALID_REASON_CAPTION" : "Valid",
							"CONCEPT_CODE" : "193022009",
							"DOMAIN_ID" : "Condition",
							"VOCABULARY_ID" : "SNOMED",
							"CONCEPT_CLASS_ID" : "Clinical Finding"
						},
						"isExcluded" : false,
						"includeDescendants" : false,
						"includeMapped" : false
					},
					{
						"concept" : {
							"CONCEPT_ID" : 4309257,
							"CONCEPT_NAME" : "Refractory localization-related epilepsy",
							"STANDARD_CONCEPT" : "S",
							"STANDARD_CONCEPT_CAPTION" : "Standard",
							"INVALID_REASON" : "V",
							"INVALID_REASON_CAPTION" : "Valid",
							"CONCEPT_CODE" : "422724001",
							"DOMAIN_ID" : "Condition",
							"VOCABULARY_ID" : "SNOMED",
							"CONCEPT_CLASS_ID" : "Clinical Finding"
						},
						"isExcluded" : false,
						"includeDescendants" : false,
						"includeMapped" : false
					},
					{
						"concept" : {
							"CONCEPT_ID" : 43530626,
							"CONCEPT_NAME" : "Simple partial seizure",
							"STANDARD_CONCEPT" : "S",
							"STANDARD_CONCEPT_CAPTION" : "Standard",
							"INVALID_REASON" : "V",
							"INVALID_REASON_CAPTION" : "Valid",
							"CONCEPT_CODE" : "117891000119100",
							"DOMAIN_ID" : "Condition",
							"VOCABULARY_ID" : "SNOMED",
							"CONCEPT_CLASS_ID" : "Clinical Finding"
						},
						"isExcluded" : false,
						"includeDescendants" : false,
						"includeMapped" : false
					},
					{
						"concept" : {
							"CONCEPT_ID" : 4236312,
							"CONCEPT_NAME" : "Complex partial epileptic seizure",
							"STANDARD_CONCEPT" : "S",
							"STANDARD_CONCEPT_CAPTION" : "Standard",
							"INVALID_REASON" : "V",
							"INVALID_REASON_CAPTION" : "Valid",
							"CONCEPT_CODE" : "407675009",
							"DOMAIN_ID" : "Condition",
							"VOCABULARY_ID" : "SNOMED",
							"CONCEPT_CLASS_ID" : "Clinical Finding"
						},
						"isExcluded" : false,
						"includeDescendants" : false,
						"includeMapped" : false
					},
					{
						"concept" : {
							"CONCEPT_ID" : 4055361,
							"CONCEPT_NAME" : "Generalized epilepsy",
							"STANDARD_CONCEPT" : "S",
							"STANDARD_CONCEPT_CAPTION" : "Standard",
							"INVALID_REASON" : "V",
							"INVALID_REASON_CAPTION" : "Valid",
							"CONCEPT_CODE" : "19598007",
							"DOMAIN_ID" : "Condition",
							"VOCABULARY_ID" : "SNOMED",
							"CONCEPT_CLASS_ID" : "Clinical Finding"
						},
						"isExcluded" : false,
						"includeDescendants" : false,
						"includeMapped" : false
					},
					{
						"concept" : {
							"CONCEPT_ID" : 4274575,
							"CONCEPT_NAME" : "Idiopathic generalized epilepsy",
							"STANDARD_CONCEPT" : "S",
							"STANDARD_CONCEPT_CAPTION" : "Standard",
							"INVALID_REASON" : "V",
							"INVALID_REASON_CAPTION" : "Valid",
							"CONCEPT_CODE" : "36803009",
							"DOMAIN_ID" : "Condition",
							"VOCABULARY_ID" : "SNOMED",
							"CONCEPT_CLASS_ID" : "Clinical Finding"
						},
						"isExcluded" : false,
						"includeDescendants" : false,
						"includeMapped" : false
					},
					{
						"concept" : {
							"CONCEPT_ID" : 374023,
							"CONCEPT_NAME" : "Epilepsia partialis continua",
							"STANDARD_CONCEPT" : "S",
							"STANDARD_CONCEPT_CAPTION" : "Standard",
							"INVALID_REASON" : "V",
							"INVALID_REASON_CAPTION" : "Valid",
							"CONCEPT_CODE" : "241006",
							"DOMAIN_ID" : "Condition",
							"VOCABULARY_ID" : "SNOMED",
							"CONCEPT_CLASS_ID" : "Clinical Finding"
						},
						"isExcluded" : false,
						"includeDescendants" : false,
						"includeMapped" : false
					},
					{
						"concept" : {
							"CONCEPT_ID" : 4047897,
							"CONCEPT_NAME" : "Epilepsy with grand mal seizures on awakening",
							"STANDARD_CONCEPT" : "S",
							"STANDARD_CONCEPT_CAPTION" : "Standard",
							"INVALID_REASON" : "V",
							"INVALID_REASON_CAPTION" : "Valid",
							"CONCEPT_CODE" : "230414008",
							"DOMAIN_ID" : "Condition",
							"VOCABULARY_ID" : "SNOMED",
							"CONCEPT_CLASS_ID" : "Clinical Finding"
						},
						"isExcluded" : false,
						"includeDescendants" : false,
						"includeMapped" : false
					},
					{
						"concept" : {
							"CONCEPT_ID" : 4179936,
							"CONCEPT_NAME" : "Childhood absence epilepsy",
							"STANDARD_CONCEPT" : "S",
							"STANDARD_CONCEPT_CAPTION" : "Standard",
							"INVALID_REASON" : "V",
							"INVALID_REASON_CAPTION" : "Valid",
							"CONCEPT_CODE" : "50866000",
							"DOMAIN_ID" : "Condition",
							"VOCABULARY_ID" : "SNOMED",
							"CONCEPT_CLASS_ID" : "Clinical Finding"
						},
						"isExcluded" : false,
						"includeDescendants" : false,
						"includeMapped" : false
					},
					{
						"concept" : {
							"CONCEPT_ID" : 376105,
							"CONCEPT_NAME" : "West syndrome",
							"STANDARD_CONCEPT" : "S",
							"STANDARD_CONCEPT_CAPTION" : "Standard",
							"INVALID_REASON" : "V",
							"INVALID_REASON_CAPTION" : "Valid",
							"CONCEPT_CODE" : "28055006",
							"DOMAIN_ID" : "Condition",
							"VOCABULARY_ID" : "SNOMED",
							"CONCEPT_CLASS_ID" : "Clinical Finding"
						},
						"isExcluded" : false,
						"includeDescendants" : false,
						"includeMapped" : false
					},
					{
						"concept" : {
							"CONCEPT_ID" : 4046213,
							"CONCEPT_NAME" : "Lennox-Gastaut syndrome",
							"STANDARD_CONCEPT" : "S",
							"STANDARD_CONCEPT_CAPTION" : "Standard",
							"INVALID_REASON" : "V",
							"INVALID_REASON_CAPTION" : "Valid",
							"CONCEPT_CODE" : "230418006",
							"DOMAIN_ID" : "Condition",
							"VOCABULARY_ID" : "SNOMED",
							"CONCEPT_CLASS_ID" : "Clinical Finding"
						},
						"isExcluded" : false,
						"includeDescendants" : false,
						"includeMapped" : false
					},
					{
						"concept" : {
							"CONCEPT_ID" : 380378,
							"CONCEPT_NAME" : "Epilepsy",
							"STANDARD_CONCEPT" : "S",
							"STANDARD_CONCEPT_CAPTION" : "Standard",
							"INVALID_REASON" : "V",
							"INVALID_REASON_CAPTION" : "Valid",
							"CONCEPT_CODE" : "84757009",
							"DOMAIN_ID" : "Condition",
							"VOCABULARY_ID" : "SNOMED",
							"CONCEPT_CLASS_ID" : "Clinical Finding"
						},
						"isExcluded" : false,
						"includeDescendants" : false,
						"includeMapped" : false
					},
					{
						"concept" : {
							"CONCEPT_ID" : 377091,
							"CONCEPT_NAME" : "Seizure",
							"STANDARD_CONCEPT" : "S",
							"STANDARD_CONCEPT_CAPTION" : "Standard",
							"INVALID_REASON" : "V",
							"INVALID_REASON_CAPTION" : "Valid",
							"CONCEPT_CODE" : "91175000",
							"DOMAIN_ID" : "Condition",
							"VOCABULARY_ID" : "SNOMED",
							"CONCEPT_CLASS_ID" : "Clinical Finding"
						},
						"isExcluded" : false,
						"includeDescendants" : false,
						"includeMapped" : false
					},
					{
						"concept" : {
							"CONCEPT_ID" : 40483317,
							"CONCEPT_NAME" : "Refractory epilepsy",
							"STANDARD_CONCEPT" : "S",
							"STANDARD_CONCEPT_CAPTION" : "Standard",
							"INVALID_REASON" : "V",
							"INVALID_REASON_CAPTION" : "Valid",
							"CONCEPT_CODE" : "445355009",
							"DOMAIN_ID" : "Condition",
							"VOCABULARY_ID" : "SNOMED",
							"CONCEPT_CLASS_ID" : "Clinical Finding"
						},
						"isExcluded" : false,
						"includeDescendants" : false,
						"includeMapped" : false
					},
					{
						"concept" : {
							"CONCEPT_ID" : 373748,
							"CONCEPT_NAME" : "Grand mal status",
							"STANDARD_CONCEPT" : "S",
							"STANDARD_CONCEPT_CAPTION" : "Standard",
							"INVALID_REASON" : "V",
							"INVALID_REASON_CAPTION" : "Valid",
							"CONCEPT_CODE" : "13973009",
							"DOMAIN_ID" : "Condition",
							"VOCABULARY_ID" : "SNOMED",
							"CONCEPT_CLASS_ID" : "Clinical Finding"
						},
						"isExcluded" : false,
						"includeDescendants" : false,
						"includeMapped" : false
					},
					{
						"concept" : {
							"CONCEPT_ID" : 381842,
							"CONCEPT_NAME" : "Petit mal status",
							"STANDARD_CONCEPT" : "S",
							"STANDARD_CONCEPT_CAPTION" : "Standard",
							"INVALID_REASON" : "V",
							"INVALID_REASON_CAPTION" : "Valid",
							"CONCEPT_CODE" : "7033004",
							"DOMAIN_ID" : "Condition",
							"VOCABULARY_ID" : "SNOMED",
							"CONCEPT_CLASS_ID" : "Clinical Finding"
						},
						"isExcluded" : false,
						"includeDescendants" : false,
						"includeMapped" : false
					},
					{
						"concept" : {
							"CONCEPT_ID" : 4043559,
							"CONCEPT_NAME" : "Complex partial status epilepticus",
							"STANDARD_CONCEPT" : "S",
							"STANDARD_CONCEPT_CAPTION" : "Standard",
							"INVALID_REASON" : "V",
							"INVALID_REASON_CAPTION" : "Valid",
							"CONCEPT_CODE" : "230460005",
							"DOMAIN_ID" : "Condition",
							"VOCABULARY_ID" : "SNOMED",
							"CONCEPT_CLASS_ID" : "Clinical Finding"
						},
						"isExcluded" : false,
						"includeDescendants" : false,
						"includeMapped" : false
					},
					{
						"concept" : {
							"CONCEPT_ID" : 4332304,
							"CONCEPT_NAME" : "Status epilepticus",
							"STANDARD_CONCEPT" : "S",
							"STANDARD_CONCEPT_CAPTION" : "Standard",
							"INVALID_REASON" : "V",
							"INVALID_REASON_CAPTION" : "Valid",
							"CONCEPT_CODE" : "230456007",
							"DOMAIN_ID" : "Condition",
							"VOCABULARY_ID" : "SNOMED",
							"CONCEPT_CLASS_ID" : "Clinical Finding"
						},
						"isExcluded" : false,
						"includeDescendants" : false,
						"includeMapped" : false
					},
					{
						"concept" : {
							"CONCEPT_ID" : 4046219,
							"CONCEPT_NAME" : "Acquired epileptic aphasia",
							"STANDARD_CONCEPT" : "S",
							"STANDARD_CONCEPT_CAPTION" : "Standard",
							"INVALID_REASON" : "V",
							"INVALID_REASON_CAPTION" : "Valid",
							"CONCEPT_CODE" : "230438007",
							"DOMAIN_ID" : "Condition",
							"VOCABULARY_ID" : "SNOMED",
							"CONCEPT_CLASS_ID" : "Clinical Finding"
						},
						"isExcluded" : false,
						"includeDescendants" : false,
						"includeMapped" : false
					}
				]
			}
		}
	],
	"QualifiedLimit" : {
		"Type" : "First"
	},
	"ExpressionLimit" : {
		"Type" : "First"
	},
	"InclusionRules" : [],
	"CensoringCriteria" : [],
	"CollapseSettings" : {
		"CollapseType" : "ERA",
		"EraPad" : 0
	},
	"CensorWindow" : {}
}